python/db/execute_wmbs_sql.py
python/db/agent/create_agent_base.py
python/db/agent/destroy_agent.py
python/db/agent/mariadb/create_agent.py
python/db/agent/oracle/create_agent.py
python/db/bossair/mariadb/create_bossair.py
python/db/bossair/oracle/create_bossair.py
python/db/dbs3buffer/mariadb/create_dbs3buffer.py
python/db/dbs3buffer/oracle/create_dbs3buffer.py
python/db/resourcecontrol/mariadb/create_resourcecontrol.py
python/db/resourcecontrol/oracle/create_resourcecontrol.py
python/db/testdb/oracle/create.py
python/db/tier0/oracle/create.py
python/db/wmbs/create_wmbs_base.py
python/db/wmbs/mariadb/create.py
python/db/wmbs/oracle/create.py
wmcoredb/__init__.py
wmcoredb/sql/mariadb/agent/create_agent.sql
wmcoredb/sql/mariadb/bossair/create_bossair.sql
wmcoredb/sql/mariadb/dbs3buffer/create_dbs3buffer.sql
wmcoredb/sql/mariadb/resourcecontrol/create_resourcecontrol.sql
wmcoredb/sql/mariadb/testdb/create_testdb.sql
wmcoredb/sql/mariadb/wmbs/create_wmbs_indexes.sql
wmcoredb/sql/mariadb/wmbs/create_wmbs_tables.sql
wmcoredb/sql/mariadb/wmbs/initial_wmbs_data.sql
wmcoredb/sql/oracle/agent/create_agent.sql
wmcoredb/sql/oracle/bossair/create_bossair.sql
wmcoredb/sql/oracle/dbs3buffer/create_dbs3buffer.sql
wmcoredb/sql/oracle/resourcecontrol/create_resourcecontrol.sql
wmcoredb/sql/oracle/testdb/create_testdb.sql
wmcoredb/sql/oracle/tier0/create_tier0_functions.sql
wmcoredb/sql/oracle/tier0/create_tier0_indexes.sql
wmcoredb/sql/oracle/tier0/create_tier0_tables.sql
wmcoredb/sql/oracle/tier0/initial_tier0_data.sql
wmcoredb/sql/oracle/wmbs/create_wmbs_indexes.sql
wmcoredb/sql/oracle/wmbs/create_wmbs_tables.sql
wmcoredb/sql/oracle/wmbs/initial_wmbs_data.sql
wmcoredb-0.9.1.dist-info/licenses/LICENSE
wmcoredb-0.9.1.dist-info/METADATA
wmcoredb-0.9.1.dist-info/WHEEL
wmcoredb-0.9.1.dist-info/top_level.txt
wmcoredb-0.9.1.dist-info/RECORD
