Metadata-Version: 2.4
Name: wmcoredb
Version: 0.9.1
Summary: WMCore Database Schema - Database schema definitions for WMCore components
Author-email: WMCore Team <cms-wmcore-team@cern.ch>
Maintainer-email: WMCore Team <cms-wmcore-team@cern.ch>
License-Expression: Apache-2.0
Project-URL: Homepage, https://github.com/dmwm/wmcoredb
Project-URL: Repository, https://github.com/dmwm/wmcoredb
Project-URL: Documentation, https://github.com/dmwm/wmcoredb#readme
Project-URL: Issues, https://github.com/dmwm/wmcoredb/issues
Project-URL: Changelog, https://github.com/dmwm/wmcoredb/releases
Keywords: database,schema,wmcore,oracle,mariadb,cms,workload-management
Classifier: Development Status :: 4 - Beta
Classifier: Intended Audience :: Developers
Classifier: Operating System :: OS Independent
Classifier: Programming Language :: Python :: 3
Classifier: Programming Language :: Python :: 3.8
Classifier: Programming Language :: Python :: 3.9
Classifier: Programming Language :: Python :: 3.10
Classifier: Programming Language :: Python :: 3.11
Classifier: Programming Language :: Python :: 3.12
Classifier: Topic :: Database
Classifier: Topic :: Software Development :: Libraries :: Python Modules
Classifier: Topic :: Scientific/Engineering :: Information Analysis
Requires-Python: >=3.8
License-File: LICENSE
Requires-Dist: setuptools>=61.0
Provides-Extra: dev
Requires-Dist: build>=0.10.0; extra == "dev"
Requires-Dist: pytest>=6.0; extra == "dev"
Requires-Dist: twine>=3.0; extra == "dev"
Dynamic: license-file
